[
    {
        "id": "1",
        "name": "Abarth"
    },
    {
        "id": "2",
        "name": "AK"
    },
    {
        "id": "3",
        "name": "Alfa Romeo"
    },
    {
        "id": "4",
        "name": "Alpine"
    },
    {
        "id": "5",
        "name": "Ariel"
    },
    {
        "id": "6",
        "name": "Aston Martin"
    },
    {
        "id": "7",
        "name": "Audi"
    },
    {
        "id": "8",
        "name": "Austin"
    },
    {
        "id": "9",
        "name": "BAC"
    },
    {
        "id": "10",
        "name": "Beauford"
    },
    {
        "id": "11",
        "name": "Bentley"
    },
    {
        "id": "12",
        "name": "BMW"
    },
    {
        "id": "13",
        "name": "Bowler"
    },
    {
        "id": "14",
        "name": "Bristol"
    },
    {
        "id": "15",
        "name": "Bugatti"
    },
    {
        "id": "16",
        "name": "Buick"
    },
    {
        "id": "17",
        "name": "Cadillac"
    },
    {
        "id": "18",
        "name": "Caterham"
    },
    {
        "id": "19",
        "name": "Chesil"
    },
    {
        "id": "20",
        "name": "Chevrolet"
    },
    {
        "id": "21",
        "name": "Chrysler"
    },
    {
        "id": "22",
        "name": "Citroen"
    },
    {
        "id": "23",
        "name": "Corvette"
    },
    {
        "id": "24",
        "name": "Cupra"
    },
    {
        "id": "25",
        "name": "Dacia"
    },
    {
        "id": "26",
        "name": "Daewoo"
    },
    {
        "id": "27",
        "name": "Daihatsu"
    },
    {
        "id": "28",
        "name": "Daimler"
    },
    {
        "id": "29",
        "name": "Dax"
    },
    {
        "id": "30",
        "name": "Delorean"
    },
    {
        "id": "31",
        "name": "Dodge"
    },
    {
        "id": "32",
        "name": "DS Automobiles"
    },
    {
        "id": "33",
        "name": "Ferrari"
    },
    {
        "id": "34",
        "name": "Fiat"
    },
    {
        "id": "35",
        "name": "Ford"
    },
    {
        "id": "36",
        "name": "GBS"
    },
    {
        "id": "37",
        "name": "GMC"
    },
    {
        "id": "38",
        "name": "Great Wall"
    },
    {
        "id": "39",
        "name": "Holden"
    },
    {
        "id": "40",
        "name": "Honda"
    },
    {
        "id": "41",
        "name": "Humber"
    },
    {
        "id": "42",
        "name": "Hummer"
    },
    {
        "id": "43",
        "name": "Hyundai"
    },
    {
        "id": "44",
        "name": "Infiniti"
    },
    {
        "id": "45",
        "name": "Isuzu"
    },
    {
        "id": "46",
        "name": "Iveco"
    },
    {
        "id": "47",
        "name": "Jaguar"
    },
    {
        "id": "48",
        "name": "Jeep"
    },
    {
        "id": "49",
        "name": "Jensen"
    },
    {
        "id": "50",
        "name": "Kia"
    },
    {
        "id": "51",
        "name": "Koenigsegg"
    },
    {
        "id": "52",
        "name": "KTM"
    },
    {
        "id": "53",
        "name": "Lada"
    },
    {
        "id": "54",
        "name": "Lamborghini"
    },
    {
        "id": "55",
        "name": "Lancia"
    },
    {
        "id": "56",
        "name": "Land Rover"
    },
    {
        "id": "57",
        "name": "Levc"
    },
    {
        "id": "58",
        "name": "Lexus"
    },
    {
        "id": "59",
        "name": "Lincoln"
    },
    {
        "id": "60",
        "name": "Lotus"
    },
    {
        "id": "61",
        "name": "Maserati"
    },
    {
        "id": "62",
        "name": "Maybach"
    },
    {
        "id": "63",
        "name": "Mazda"
    },
    {
        "id": "64",
        "name": "McLaren"
    },
    {
        "id": "65",
        "name": "Mercedes-Benz"
    },
    {
        "id": "66",
        "name": "Messerschmitt"
    },
    {
        "id": "67",
        "name": "MG"
    },
    {
        "id": "68",
        "name": "Microcar"
    },
    {
        "id": "69",
        "name": "Mini"
    },
    {
        "id": "70",
        "name": "Mitsubishi"
    },
    {
        "id": "71",
        "name": "MK"
    },
    {
        "id": "72",
        "name": "Morgan"
    },
    {
        "id": "73",
        "name": "Morris"
    },
    {
        "id": "74",
        "name": "Nissan"
    },
    {
        "id": "75",
        "name": "Noble"
    },
    {
        "id": "76",
        "name": "Opel"
    },
    {
        "id": "77",
        "name": "Perodua"
    },
    {
        "id": "78",
        "name": "Peugeot"
    },
    {
        "id": "79",
        "name": "Pilgrim"
    },
    {
        "id": "80",
        "name": "Pontiac"
    },
    {
        "id": "81",
        "name": "Porsche"
    },
    {
        "id": "82",
        "name": "Proton"
    },
    {
        "id": "83",
        "name": "Radical"
    },
    {
        "id": "84",
        "name": "Raw"
    },
    {
        "id": "85",
        "name": "Reliant"
    },
    {
        "id": "86",
        "name": "Renault"
    },
    {
        "id": "87",
        "name": "Replica"
    },
    {
        "id": "88",
        "name": "Riley"
    },
    {
        "id": "89",
        "name": "Robin Hood"
    },
    {
        "id": "90",
        "name": "Rolls-Royce"
    },
    {
        "id": "91",
        "name": "Rover"
    },
    {
        "id": "92",
        "name": "Saab"
    },
    {
        "id": "93",
        "name": "Seat"
    },
    {
        "id": "94",
        "name": "Singer"
    },
    {
        "id": "95",
        "name": "Skoda"
    },
    {
        "id": "96",
        "name": "Smart"
    },
    {
        "id": "97",
        "name": "Ssangyong"
    },
    {
        "id": "98",
        "name": "Standard"
    },
    {
        "id": "99",
        "name": "Subaru"
    },
    {
        "id": "100",
        "name": "Sunbeam"
    },
    {
        "id": "101",
        "name": "Suzuki"
    },
    {
        "id": "102",
        "name": "Tesla"
    },
    {
        "id": "103",
        "name": "Tiger"
    },
    {
        "id": "104",
        "name": "Toyota"
    },
    {
        "id": "105",
        "name": "Triumph"
    },
    {
        "id": "106",
        "name": "TVR"
    },
    {
        "id": "107",
        "name": "Vauxhall"
    },
    {
        "id": "108",
        "name": "Volkswagen"
    },
    {
        "id": "109",
        "name": "Volvo"
    },
    {
        "id": "110",
        "name": "Westfield"
    },
    {
        "id": "111",
        "name": "Zenos"
    }
]
